MANIFEST.in
README.rst
setup.py
bin/telomerehunter
telomerehunter/__init__.py
telomerehunter/check_R_libraries.R
telomerehunter/estimate_telomere_content.py
telomerehunter/filter_telomere_reads.py
telomerehunter/functions_for_plots.R
telomerehunter/get_repeat_threshold.py
telomerehunter/hg19_cytoBand.txt
telomerehunter/merge_pdfs.py
telomerehunter/plot_gc_content.R
telomerehunter/plot_repeat_frequency_intratelomeric.R
telomerehunter/plot_spectrum.R
telomerehunter/plot_spectrum_summary.R
telomerehunter/plot_tel_content.R
telomerehunter/repeat_frequency_intratelomeric.py
telomerehunter/sort_telomere_reads.py
telomerehunter.egg-info/PKG-INFO
telomerehunter.egg-info/SOURCES.txt
telomerehunter.egg-info/dependency_links.txt
telomerehunter.egg-info/not-zip-safe
telomerehunter.egg-info/requires.txt
telomerehunter.egg-info/top_level.txt