Metadata-Version: 1.0
Name: telomerehunter
Version: 1.0.1
Summary: Estimation of Telomere Content from WGS Data
Home-page: https://pypi.python.org/pypi/telomerehunter/
Author: Lars Feuerbach <l.feuerbach@dkfz-heidelberg.de>, Philip Ginsbach, Lina Sieverling <l.sieverling@dkfz-heidelberg.de>
Author-email: l.sieverling@dkfz-heidelberg.de
License: GPL
Keywords: telomere content read NGS WGS tumor control
Platform: UNKNOWN
